ifd/__init__.py
ifd/entities/Abstract/ADetection.py
ifd/entities/Abstract/__init__.py
ifd/entities/BodyTicket.py
ifd/entities/Classification.py
ifd/entities/Couleur.py
ifd/entities/Detection.py
ifd/entities/Image.py
ifd/entities/Intervention.py
ifd/entities/LogResult.py
ifd/entities/Malfacon.py
ifd/entities/Modele.py
ifd/entities/OCR.py
ifd/entities/RabbitMqMessage.py
ifd/entities/Tag.py
ifd/entities/Ticket.py
ifd/entities/__init__.py
ifd/entities/bbox.py
ifd/repository/AmqpImageRepository.py
ifd/repository/RestTicketRepository.py
ifd/repository/SqlLogRepository.py
ifd/repository/SqlTicketRepository.py
ifd/repository/__init__.py
ifd/repository/abstract/AbsSqlRepository.py
ifd/repository/abstract/__init__.py
ifd/spec.py
ifd/tools.py
ifd/usecase/Interfaces/IFonction.py
ifd/usecase/Interfaces/__init__.py
ifd/usecase/__init__.py
ifd_python-10.1.14.dist-info/LICENSE
ifd_python-10.1.14.dist-info/METADATA
ifd_python-10.1.14.dist-info/WHEEL
ifd_python-10.1.14.dist-info/RECORD
