Metadata-Version: 2.1
Name: ifd-python
Version: 10.1.14
Summary: 
Author: Antonin Lemoine
Author-email: antonin.lemoine@altitudeinfra.fr
Requires-Python: >=3.6,<4.0
Classifier: Programming Language :: Python :: 3
Classifier: Programming Language :: Python :: 3.6
Classifier: Programming Language :: Python :: 3.7
Classifier: Programming Language :: Python :: 3.8
Classifier: Programming Language :: Python :: 3.9
Classifier: Programming Language :: Python :: 3.10
Classifier: Programming Language :: Python :: 3.11
Requires-Dist: pandas (>=2.0.0,<3.0.0)
Requires-Dist: pika (>=1.3.0,<2.0.0)
Requires-Dist: pymssql (>=2.0.0,<3.0.0)
Requires-Dist: requests (>=2.0.0,<3.0.0)
